setup.py
galaxy_mgp/__init__.py
galaxy_mgp/earth_test.py
galaxy_mgp.egg-info/PKG-INFO
galaxy_mgp.egg-info/SOURCES.txt
galaxy_mgp.egg-info/dependency_links.txt
galaxy_mgp.egg-info/not-zip-safe
galaxy_mgp.egg-info/top_level.txt