Metadata-Version: 1.0
Name: galaxy-mgp
Version: 0.1.1
Summary: The plathora distanced
Home-page: http://github.com/mgpradeepa/py_pip
Author: MGP
Author-email: mgpradeepa@gmail.com
License: UNKNOWN
Platform: UNKNOWN
